README.rst
setup.py
RequireType.egg-info/PKG-INFO
RequireType.egg-info/SOURCES.txt
RequireType.egg-info/dependency_links.txt
RequireType.egg-info/not-zip-safe
RequireType.egg-info/pbr.json
RequireType.egg-info/top_level.txt
requiretype/__init__.py
requiretype/requiretype.py