Metadata-Version: 1.1
Name: RequireType
Version: 0.1.0
Summary: UNKNOWN
Home-page: https://github.com/ivanalejandro0/RequireType
Author: Ivan Alejandro
Author-email: ivanalejandro0@gmail.com
License: BSD
Keywords: requiretype
Platform: UNKNOWN
Classifier: Development Status :: 2 - Pre-Alpha
Classifier: Intended Audience :: Developers
Classifier: License :: OSI Approved :: BSD License
Classifier: Natural Language :: English
Classifier: Programming Language :: Python :: 2
Classifier: Programming Language :: Python :: 2.7
